django_postmark_utils/__init__.py
django_postmark_utils/admin.py
django_postmark_utils/app_settings.py
django_postmark_utils/apps.py
django_postmark_utils/models.py
django_postmark_utils/signal_handlers.py
django_postmark_utils/tests.py
django_postmark_utils/urls.py
django_postmark_utils/utils.py
django_postmark_utils/views.py
django_postmark_utils/management/__init__.py
django_postmark_utils/management/commands/__init__.py
django_postmark_utils/management/commands/purge_postmark_messages.py
django_postmark_utils/migrations/0001_initial.py
django_postmark_utils/migrations/0002_message_created.py
django_postmark_utils/migrations/__init__.py
django_postmark_utils-0.1.dist-info/DESCRIPTION.rst
django_postmark_utils-0.1.dist-info/METADATA
django_postmark_utils-0.1.dist-info/RECORD
django_postmark_utils-0.1.dist-info/WHEEL
django_postmark_utils-0.1.dist-info/metadata.json
django_postmark_utils-0.1.dist-info/top_level.txt
